zpipe/__init__.py
zpipe/pipeline.py
zpipe/setup.py
zpipe/worker.py
zpipe/stages/__init__.py
zpipe/stages/nonworker_stage.py
zpipe/stages/stage.py
zpipe/stages/stage_class.py
zpipe/stages/worker_stage.py
zpipe/utils/__init__.py
zpipe/utils/pickles.py
zpipe/utils/ztypes.py
pyzpipe-0.2.3.1.dist-info/LICENSE
pyzpipe-0.2.3.1.dist-info/METADATA
pyzpipe-0.2.3.1.dist-info/WHEEL
pyzpipe-0.2.3.1.dist-info/top_level.txt
pyzpipe-0.2.3.1.dist-info/RECORD
